Tarea08/src/probador.v
module probador(
    input [4:0] salida_gray_synth,
    input [4:0] salida_gray_con,
    input outChecker,
    output reg enable,
    output reg reset_L,
    output reg clk
	);

    initial begin
        $dumpfile ("prueba_1.vcd");
        $dumpvars;

        {reset_L, enable} = 1'b0;

        @(posedge clk)
            reset_L <= 1;

        @(posedge clk)
            enable <= 1;

        repeat (500) begin
            @(posedge clk);
        end 


        $finish;
    end

    initial	clk 	<= 0;			// Valor inicial al reloj.
	always	#5 clk 	<= ~clk;		// Hace "toggle" cada 2*10ns
endmodule

Tarea08/src/checker.v
module checker (
    output reg outChecker,
    input [4:0] in_1,
    input [4:0] in_2,
    input clk);

    always @ (posedge clk) 
        begin
            if (in_1[4:0] == in_2[4:0])
                outChecker <= 1;
            else
                outChecker <= 0;
        end
endmodule

Tarea08/src/contador_gray_synth.v
(* top =  1  *)
(* src = "contador_gray_synth.v:1" *)
module contador_gray_synth(clk, reset_L, enable, salida_gray_synth);
  (* src = "contador_gray_synth.v:10" *)
  wire [4:0] _000_;
  (* src = "contador_gray_synth.v:10" *)
  wire [1:0] _001_;
  wire _002_;
  wire _003_;
  wire _004_;
  wire _005_;
  wire _006_;
  wire _007_;
  wire _008_;
  wire _009_;
  wire _010_;
  wire _011_;
  wire _012_;
  wire _013_;
  wire _014_;
  wire _015_;
  wire _016_;
  wire _017_;
  wire _018_;
  wire _019_;
  wire _020_;
  wire _021_;
  wire _022_;
  wire _023_;
  wire _024_;
  wire _025_;
  wire _026_;
  wire _027_;
  wire _028_;
  wire _029_;
  wire _030_;
  wire _031_;
  wire _032_;
  wire _033_;
  wire _034_;
  wire _035_;
  wire _036_;
  wire _037_;
  wire _038_;
  wire _039_;
  wire _040_;
  wire _041_;
  wire _042_;
  wire _043_;
  wire _044_;
  wire _045_;
  wire _046_;
  (* src = "contador_gray_synth.v:2" *)
  input clk;
  (* src = "contador_gray_synth.v:7" *)
  wire [4:0] count;
  (* src = "contador_gray_synth.v:4" *)
  input enable;
  (* src = "contador_gray_synth.v:3" *)
  input reset_L;
  (* src = "contador_gray_synth.v:5" *)
  output [4:0] salida_gray_synth;
  (* src = "contador_gray_synth.v:8" *)
  wire [1:0] xor_output_cnt;
  NOT _047_ (
    .A(count[3]),
    .Y(_002_)
  );
  NOT _048_ (
    .A(xor_output_cnt[0]),
    .Y(_003_)
  );
  NOT _049_ (
    .A(xor_output_cnt[1]),
    .Y(_004_)
  );
  NOT _050_ (
    .A(count[1]),
    .Y(_005_)
  );
  NOT _051_ (
    .A(count[2]),
    .Y(_006_)
  );
  NAND _052_ (
    .A(enable),
    .B(count[0]),
    .Y(_007_)
  );
  NOT _053_ (
    .A(_007_),
    .Y(_008_)
  );
  NOR _054_ (
    .A(_005_),
    .B(_006_),
    .Y(_009_)
  );
  NAND _055_ (
    .A(count[1]),
    .B(count[2]),
    .Y(_010_)
  );
  NAND _056_ (
    .A(_008_),
    .B(_009_),
    .Y(_011_)
  );
  NAND _057_ (
    .A(count[3]),
    .B(count[4]),
    .Y(_012_)
  );
  NOT _058_ (
    .A(_012_),
    .Y(_013_)
  );
  NAND _059_ (
    .A(count[0]),
    .B(count[1]),
    .Y(_014_)
  );
  NOR _060_ (
    .A(_005_),
    .B(_007_),
    .Y(_015_)
  );
  NAND _061_ (
    .A(count[3]),
    .B(count[2]),
    .Y(_016_)
  );
  NOT _062_ (
    .A(_016_),
    .Y(_017_)
  );
  NOR _063_ (
    .A(_002_),
    .B(_011_),
    .Y(_018_)
  );
  NOR _064_ (
    .A(_011_),
    .B(_012_),
    .Y(_019_)
  );
  NAND _065_ (
    .A(count[4]),
    .B(_018_),
    .Y(_020_)
  );
  NOR _066_ (
    .A(_003_),
    .B(_020_),
    .Y(_021_)
  );
  NAND _067_ (
    .A(xor_output_cnt[0]),
    .B(_019_),
    .Y(_022_)
  );
  NAND _068_ (
    .A(_003_),
    .B(_020_),
    .Y(_023_)
  );
  NAND _069_ (
    .A(reset_L),
    .B(_023_),
    .Y(_024_)
  );
  NOR _070_ (
    .A(_021_),
    .B(_024_),
    .Y(_001_[0])
  );
  NOR _071_ (
    .A(_004_),
    .B(_022_),
    .Y(_025_)
  );
  NAND _072_ (
    .A(_004_),
    .B(_022_),
    .Y(_026_)
  );
  NAND _073_ (
    .A(reset_L),
    .B(_026_),
    .Y(_027_)
  );
  NOR _074_ (
    .A(_025_),
    .B(_027_),
    .Y(_001_[1])
  );
  NOR _075_ (
    .A(enable),
    .B(count[0]),
    .Y(_028_)
  );
  NAND _076_ (
    .A(reset_L),
    .B(_007_),
    .Y(_029_)
  );
  NOR _077_ (
    .A(_028_),
    .B(_029_),
    .Y(_000_[0])
  );
  NAND _078_ (
    .A(_005_),
    .B(_007_),
    .Y(_030_)
  );
  NAND _079_ (
    .A(reset_L),
    .B(_030_),
    .Y(_031_)
  );
  NOR _080_ (
    .A(_015_),
    .B(_031_),
    .Y(_000_[1])
  );
  NOR _081_ (
    .A(count[2]),
    .B(_015_),
    .Y(_032_)
  );
  NAND _082_ (
    .A(reset_L),
    .B(_011_),
    .Y(_033_)
  );
  NOR _083_ (
    .A(_032_),
    .B(_033_),
    .Y(_000_[2])
  );
  NAND _084_ (
    .A(_002_),
    .B(_011_),
    .Y(_034_)
  );
  NAND _085_ (
    .A(reset_L),
    .B(_034_),
    .Y(_035_)
  );
  NOR _086_ (
    .A(_018_),
    .B(_035_),
    .Y(_000_[3])
  );
  NOR _087_ (
    .A(count[4]),
    .B(_018_),
    .Y(_036_)
  );
  NAND _088_ (
    .A(reset_L),
    .B(_020_),
    .Y(_037_)
  );
  NOR _089_ (
    .A(_036_),
    .B(_037_),
    .Y(_000_[4])
  );
  NOR _090_ (
    .A(count[0]),
    .B(count[1]),
    .Y(_038_)
  );
  NOR _091_ (
    .A(count[3]),
    .B(count[4]),
    .Y(_039_)
  );
  NAND _092_ (
    .A(_003_),
    .B(xor_output_cnt[1]),
    .Y(_040_)
  );
  NOR _093_ (
    .A(_010_),
    .B(_040_),
    .Y(_041_)
  );
  NAND _094_ (
    .A(_039_),
    .B(_041_),
    .Y(_042_)
  );
  NOT _095_ (
    .A(_042_),
    .Y(_043_)
  );
  NOR _096_ (
    .A(_014_),
    .B(_043_),
    .Y(_044_)
  );
  NOR _097_ (
    .A(_038_),
    .B(_044_),
    .Y(salida_gray_synth[0])
  );
  NOR _098_ (
    .A(count[1]),
    .B(count[2]),
    .Y(_045_)
  );
  NOR _099_ (
    .A(_009_),
    .B(_045_),
    .Y(salida_gray_synth[1])
  );
  NOR _100_ (
    .A(count[3]),
    .B(count[2]),
    .Y(_046_)
  );
  NOR _101_ (
    .A(_017_),
    .B(_046_),
    .Y(salida_gray_synth[2])
  );
  NOR _102_ (
    .A(_013_),
    .B(_039_),
    .Y(salida_gray_synth[3])
  );
  (* src = "contador_gray_synth.v:10" *)
  DFF _103_ (
    .C(clk),
    .D(_000_[0]),
    .Q(count[0])
  );
  (* src = "contador_gray_synth.v:10" *)
  DFF _104_ (
    .C(clk),
    .D(_000_[1]),
    .Q(count[1])
  );
  (* src = "contador_gray_synth.v:10" *)
  DFF _105_ (
    .C(clk),
    .D(_000_[2]),
    .Q(count[2])
  );
  (* src = "contador_gray_synth.v:10" *)
  DFF _106_ (
    .C(clk),
    .D(_000_[3]),
    .Q(count[3])
  );
  (* src = "contador_gray_synth.v:10" *)
  DFF _107_ (
    .C(clk),
    .D(_000_[4]),
    .Q(count[4])
  );
  (* src = "contador_gray_synth.v:10" *)
  DFF _108_ (
    .C(clk),
    .D(_001_[0]),
    .Q(xor_output_cnt[0])
  );
  (* src = "contador_gray_synth.v:10" *)
  DFF _109_ (
    .C(clk),
    .D(_001_[1]),
    .Q(xor_output_cnt[1])
  );
  assign salida_gray_synth[4] = count[4];
endmodule

Tarea08/src/contador_gray_con.v
module contador_gray_cond(
                    input clk,
                    input reset_L,
                    input enable,
                    output reg [4:0] salida_gray
                    );
    
    reg [4:0] contador_bin;
    
    always @(posedge clk)begin

        if (reset_L == 0 || enable == 0)begin
            contador_bin <= 0;
            salida_gray <= 0;
        end
        else if (reset_L == 1 && enable == 1)begin
            contador_bin = contador_bin + 1;
            salida_gray [4] <= contador_bin[4];
            salida_gray [3] <= contador_bin[4] + contador_bin[3];
            salida_gray [2] <= contador_bin[3] + contador_bin[2];
            salida_gray [1] <= contador_bin[2] + contador_bin[1];
            salida_gray [0] <= contador_bin[1] + contador_bin[0];   
        end
    end
endmodule

Tarea08/src/BancoPrueba.v
`timescale 	1ns	/ 1ns

`include "contador_gray_synth.v"
`include "contador_gray_con.v"
`include "checker.v"
`include "cmos_cells.v"
`include "probador.v"


module BancoPrueba;
	wire clk, reset_L, enable, outChecker;
	wire [4:0] salida_gray_cond, salida_gray_synth;

	contador_gray_cond						contador_cond( /*AUTOINST*/
								      // Outputs
								      .salida_gray		(salida_gray_cond[4:0]),
								      // Inputs
								      .enable		(enable),
								      .clk				(clk),
								      .reset_L		(reset_L));

	contador_gray_synth					contador_synth( /*AUTOINST*/
								      // Outputs
								      .salida_gray_synth		(salida_gray_synth[4:0]),
								      // Inputs
								      .enable		(enable),
								      .clk				(clk),
								      .reset_L		(reset_L));

	checker check(
		//Outputs
		.outChecker (outChecker),
		//Inputs
		.clk  (clk),
		.in_1 (salida_gray_cond[4:0]),
		.in_2 (salida_gray_synth[4:0])
	);


	probador 				probador( /*AUTOINST*/
							 // Outputs
							 .enable		(enable),
							 .reset_L		(reset_L),
							 .clk			(clk),
							 // Inputs
							 .salida_gray_con		(salida_gray_cond[4:0]),
							 .salida_gray_synth		(salida_gray_synth[4:0]));
endmodule

Tarea05/src/YOSYS/cmos_cells.v
module BUF(A, Y);
input A;
output Y;
assign Y = A;
endmodule

module NOT(A, Y);
input A;
output Y;
assign #(2:4.2:6.4,2:4.2:6.4) Y = ~A;
endmodule

module NAND(A, B, Y);
input A, B;
output Y;
assign #(1:4.75:8.5,1:4.75:8.5) Y = ~(A & B);
endmodule

module NOR(A, B, Y);
input A, B;
output Y;
assign #(0.9:2.65:4.4,0.9:2.65:4.4) Y = ~(A | B);
endmodule

module DFF(C, D, Q);
input C, D;
output reg Q;
always @(posedge C)
	#5 Q <= D;
endmodule

module DFFSR(C, D, Q, S, R);
input C, D, S, R;
output reg Q;
always @(posedge C, posedge S, posedge R)
	if (S)
		Q <= 1'b1;
	else if (R)
		Q <= 1'b0;
	else
		Q <= D;
endmodule

Tarea08/src/prueba_1.vcd
$date
	Mon Jun 21 12:20:23 2021
$end
$version
	Icarus Verilog
$end
$timescale
	1ns
$end
$scope module BUF $end
$var wire 1 ! A $end
$var wire 1 " Y $end
$upscope $end
$scope module BancoPrueba $end
$var wire 5 # salida_gray_synth [4:0] $end
$var wire 5 $ salida_gray_cond [4:0] $end
$var wire 1 % reset_L $end
$var wire 1 & outChecker $end
$var wire 1 ' enable $end
$var wire 1 ( clk $end
$scope module check $end
$var wire 5 ) in_2 [4:0] $end
$var wire 5 * in_1 [4:0] $end
$var wire 1 ( clk $end
$var reg 1 & outChecker $end
$upscope $end
$scope module contador_cond $end
$var wire 1 % reset_L $end
$var wire 1 ' enable $end
$var wire 1 ( clk $end
$var reg 5 + contador_bin [4:0] $end
$var reg 5 , salida_gray [4:0] $end
$upscope $end
$scope module contador_synth $end
$var wire 2 - xor_output_cnt [1:0] $end
$var wire 5 . salida_gray_synth [4:0] $end
$var wire 1 % reset_L $end
$var wire 1 ' enable $end
$var wire 5 / count [4:0] $end
$var wire 1 ( clk $end
$var wire 1 0 _046_ $end
$var wire 1 1 _045_ $end
$var wire 1 2 _044_ $end
$var wire 1 3 _043_ $end
$var wire 1 4 _042_ $end
$var wire 1 5 _041_ $end
$var wire 1 6 _040_ $end
$var wire 1 7 _039_ $end
$var wire 1 8 _038_ $end
$var wire 1 9 _037_ $end
$var wire 1 : _036_ $end
$var wire 1 ; _035_ $end
$var wire 1 < _034_ $end
$var wire 1 = _033_ $end
$var wire 1 > _032_ $end
$var wire 1 ? _031_ $end
$var wire 1 @ _030_ $end
$var wire 1 A _029_ $end
$var wire 1 B _028_ $end
$var wire 1 C _027_ $end
$var wire 1 D _026_ $end
$var wire 1 E _025_ $end
$var wire 1 F _024_ $end
$var wire 1 G _023_ $end
$var wire 1 H _022_ $end
$var wire 1 I _021_ $end
$var wire 1 J _020_ $end
$var wire 1 K _019_ $end
$var wire 1 L _018_ $end
$var wire 1 M _017_ $end
$var wire 1 N _016_ $end
$var wire 1 O _015_ $end
$var wire 1 P _014_ $end
$var wire 1 Q _013_ $end
$var wire 1 R _012_ $end
$var wire 1 S _011_ $end
$var wire 1 T _010_ $end
$var wire 1 U _009_ $end
$var wire 1 V _008_ $end
$var wire 1 W _007_ $end
$var wire 1 X _006_ $end
$var wire 1 Y _005_ $end
$var wire 1 Z _004_ $end
$var wire 1 [ _003_ $end
$var wire 1 \ _002_ $end
$var wire 2 ] _001_ [1:0] $end
$var wire 5 ^ _000_ [4:0] $end
$scope module _047_ $end
$var wire 1 _ A $end
$var wire 1 \ Y $end
$upscope $end
$scope module _048_ $end
$var wire 1 ` A $end
$var wire 1 [ Y $end
$upscope $end
$scope module _049_ $end
$var wire 1 a A $end
$var wire 1 Z Y $end
$upscope $end
$scope module _050_ $end
$var wire 1 b A $end
$var wire 1 Y Y $end
$upscope $end
$scope module _051_ $end
$var wire 1 c A $end
$var wire 1 X Y $end
$upscope $end
$scope module _052_ $end
$var wire 1 d B $end
$var wire 1 W Y $end
$var wire 1 ' A $end
$upscope $end
$scope module _053_ $end
$var wire 1 W A $end
$var wire 1 V Y $end
$upscope $end
$scope module _054_ $end
$var wire 1 Y A $end
$var wire 1 X B $end
$var wire 1 U Y $end
$upscope $end
$scope module _055_ $end
$var wire 1 e A $end
$var wire 1 f B $end
$var wire 1 T Y $end
$upscope $end
$scope module _056_ $end
$var wire 1 V A $end
$var wire 1 U B $end
$var wire 1 S Y $end
$upscope $end
$scope module _057_ $end
$var wire 1 g A $end
$var wire 1 h B $end
$var wire 1 R Y $end
$upscope $end
$scope module _058_ $end
$var wire 1 R A $end
$var wire 1 Q Y $end
$upscope $end
$scope module _059_ $end
$var wire 1 i A $end
$var wire 1 j B $end
$var wire 1 P Y $end
$upscope $end
$scope module _060_ $end
$var wire 1 Y A $end
$var wire 1 W B $end
$var wire 1 O Y $end
$upscope $end
$scope module _061_ $end
$var wire 1 k A $end
$var wire 1 l B $end
$var wire 1 N Y $end
$upscope $end
$scope module _062_ $end
$var wire 1 N A $end
$var wire 1 M Y $end
$upscope $end
$scope module _063_ $end
$var wire 1 \ A $end
$var wire 1 S B $end
$var wire 1 L Y $end
$upscope $end
$scope module _064_ $end
$var wire 1 S A $end
$var wire 1 R B $end
$var wire 1 K Y $end
$upscope $end
$scope module _065_ $end
$var wire 1 m A $end
$var wire 1 L B $end
$var wire 1 J Y $end
$upscope $end
$scope module _066_ $end
$var wire 1 [ A $end
$var wire 1 J B $end
$var wire 1 I Y $end
$upscope $end
$scope module _067_ $end
$var wire 1 n A $end
$var wire 1 K B $end
$var wire 1 H Y $end
$upscope $end
$scope module _068_ $end
$var wire 1 [ A $end
$var wire 1 J B $end
$var wire 1 G Y $end
$upscope $end
$scope module _069_ $end
$var wire 1 G B $end
$var wire 1 F Y $end
$var wire 1 % A $end
$upscope $end
$scope module _070_ $end
$var wire 1 I A $end
$var wire 1 F B $end
$var wire 1 o Y $end
$upscope $end
$scope module _071_ $end
$var wire 1 Z A $end
$var wire 1 H B $end
$var wire 1 E Y $end
$upscope $end
$scope module _072_ $end
$var wire 1 Z A $end
$var wire 1 H B $end
$var wire 1 D Y $end
$upscope $end
$scope module _073_ $end
$var wire 1 D B $end
$var wire 1 C Y $end
$var wire 1 % A $end
$upscope $end
$scope module _074_ $end
$var wire 1 E A $end
$var wire 1 C B $end
$var wire 1 p Y $end
$upscope $end
$scope module _075_ $end
$var wire 1 q B $end
$var wire 1 B Y $end
$var wire 1 ' A $end
$upscope $end
$scope module _076_ $end
$var wire 1 W B $end
$var wire 1 A Y $end
$var wire 1 % A $end
$upscope $end
$scope module _077_ $end
$var wire 1 B A $end
$var wire 1 A B $end
$var wire 1 r Y $end
$upscope $end
$scope module _078_ $end
$var wire 1 Y A $end
$var wire 1 W B $end
$var wire 1 @ Y $end
$upscope $end
$scope module _079_ $end
$var wire 1 @ B $end
$var wire 1 ? Y $end
$var wire 1 % A $end
$upscope $end
$scope module _080_ $end
$var wire 1 O A $end
$var wire 1 ? B $end
$var wire 1 s Y $end
$upscope $end
$scope module _081_ $end
$var wire 1 t A $end
$var wire 1 O B $end
$var wire 1 > Y $end
$upscope $end
$scope module _082_ $end
$var wire 1 S B $end
$var wire 1 = Y $end
$var wire 1 % A $end
$upscope $end
$scope module _083_ $end
$var wire 1 > A $end
$var wire 1 = B $end
$var wire 1 u Y $end
$upscope $end
$scope module _084_ $end
$var wire 1 \ A $end
$var wire 1 S B $end
$var wire 1 < Y $end
$upscope $end
$scope module _085_ $end
$var wire 1 < B $end
$var wire 1 ; Y $end
$var wire 1 % A $end
$upscope $end
$scope module _086_ $end
$var wire 1 L A $end
$var wire 1 ; B $end
$var wire 1 v Y $end
$upscope $end
$scope module _087_ $end
$var wire 1 w A $end
$var wire 1 L B $end
$var wire 1 : Y $end
$upscope $end
$scope module _088_ $end
$var wire 1 J B $end
$var wire 1 9 Y $end
$var wire 1 % A $end
$upscope $end
$scope module _089_ $end
$var wire 1 : A $end
$var wire 1 9 B $end
$var wire 1 x Y $end
$upscope $end
$scope module _090_ $end
$var wire 1 y A $end
$var wire 1 z B $end
$var wire 1 8 Y $end
$upscope $end
$scope module _091_ $end
$var wire 1 { A $end
$var wire 1 | B $end
$var wire 1 7 Y $end
$upscope $end
$scope module _092_ $end
$var wire 1 [ A $end
$var wire 1 } B $end
$var wire 1 6 Y $end
$upscope $end
$scope module _093_ $end
$var wire 1 T A $end
$var wire 1 6 B $end
$var wire 1 5 Y $end
$upscope $end
$scope module _094_ $end
$var wire 1 7 A $end
$var wire 1 5 B $end
$var wire 1 4 Y $end
$upscope $end
$scope module _095_ $end
$var wire 1 4 A $end
$var wire 1 3 Y $end
$upscope $end
$scope module _096_ $end
$var wire 1 P A $end
$var wire 1 3 B $end
$var wire 1 2 Y $end
$upscope $end
$scope module _097_ $end
$var wire 1 8 A $end
$var wire 1 2 B $end
$var wire 1 ~ Y $end
$upscope $end
$scope module _098_ $end
$var wire 1 !" A $end
$var wire 1 "" B $end
$var wire 1 1 Y $end
$upscope $end
$scope module _099_ $end
$var wire 1 U A $end
$var wire 1 1 B $end
$var wire 1 #" Y $end
$upscope $end
$scope module _100_ $end
$var wire 1 $" A $end
$var wire 1 %" B $end
$var wire 1 0 Y $end
$upscope $end
$scope module _101_ $end
$var wire 1 M A $end
$var wire 1 0 B $end
$var wire 1 &" Y $end
$upscope $end
$scope module _102_ $end
$var wire 1 Q A $end
$var wire 1 7 B $end
$var wire 1 '" Y $end
$upscope $end
$scope module _103_ $end
$var wire 1 (" D $end
$var wire 1 ( C $end
$var reg 1 )" Q $end
$upscope $end
$scope module _104_ $end
$var wire 1 *" D $end
$var wire 1 ( C $end
$var reg 1 +" Q $end
$upscope $end
$scope module _105_ $end
$var wire 1 ," D $end
$var wire 1 ( C $end
$var reg 1 -" Q $end
$upscope $end
$scope module _106_ $end
$var wire 1 ." D $end
$var wire 1 ( C $end
$var reg 1 /" Q $end
$upscope $end
$scope module _107_ $end
$var wire 1 0" D $end
$var wire 1 ( C $end
$var reg 1 1" Q $end
$upscope $end
$scope module _108_ $end
$var wire 1 2" D $end
$var wire 1 ( C $end
$var reg 1 3" Q $end
$upscope $end
$scope module _109_ $end
$var wire 1 4" D $end
$var wire 1 ( C $end
$var reg 1 5" Q $end
$upscope $end
$upscope $end
$scope module probador $end
$var wire 1 6" outChecker $end
$var wire 5 7" salida_gray_con [4:0] $end
$var wire 5 8" salida_gray_synth [4:0] $end
$var reg 1 ( clk $end
$var reg 1 ' enable $end
$var reg 1 % reset_L $end
$upscope $end
$upscope $end
$scope module DFFSR $end
$var wire 1 9" C $end
$var wire 1 :" D $end
$var wire 1 ;" R $end
$var wire 1 <" S $end
$var reg 1 =" Q $end
$upscope $end
$enddefinitions $end
#0
$dumpvars
x="
z<"
z;"
z:"
z9"
bx 8"
bx 7"
z6"
x5"
04"
x3"
02"
x1"
00"
x/"
0."
x-"
0,"
x+"
0*"
x)"
0("
x'"
x&"
x%"
x$"
x#"
x""
x!"
x~
x}
x|
x{
xz
xy
0x
xw
0v
0u
xt
0s
0r
xq
0p
0o
xn
xm
xl
xk
xj
xi
xh
xg
xf
xe
xd
xc
xb
xa
x`
x_
b0 ^
b0 ]
x\
x[
xZ
xY
xX
1W
0V
xU
xT
1S
xR
xQ
xP
0O
xN
xM
0L
0K
1J
0I
1H
xG
1F
0E
xD
1C
xB
1A
x@
1?
x>
1=
x<
1;
x:
19
x8
x7
x6
x5
x4
x3
x2
x1
x0
bx /
bx .
bx -
bx ,
bx +
bx *
bx )
0(
0'
x&
0%
bx $
bx #
z"
z!
$end
#5
03
14
0~
02
0#"
0&"
0'"
05
00"
0."
0,"
0*"
0("
04"
02"
0@
0U
0M
0<
0Q
0G
0D
0x
0v
0u
0s
b0 ^
0r
0p
b0 ]
0o
1B
18
1P
11
1>
1T
10
1N
17
1:
1R
16
1Y
1X
1\
1[
1Z
09
1;
0=
1?
0A
1C
1F
0y
0q
0i
0d
0!"
0z
0j
0e
0b
0%"
0""
0t
0l
0f
0c
0$"
0{
0k
0g
0_
b0 #
b0 )
b0 .
b0 8"
0|
0w
0m
0h
0n
0`
0}
0a
b0 $
b0 *
b0 ,
b0 7"
b0 +
0)"
0+"
0-"
0/"
b0 /
01"
03"
b0 -
05"
0&
1%
1(
#10
0(
#15
1("
b1 ^
1r
0B
1'
1&
1(
#20
0(
#25
1*"
1s
0("
b10 ^
0r
0?
b1 #
b1 )
b1 .
b1 8"
1~
1A
1@
1V
08
0W
1y
1q
1i
1d
b1 $
b1 *
b1 ,
b1 7"
b1 /
1)"
b1 +
1(
#30
0(
#35
1("
b11 ^
1r
b11 #
b11 )
b11 .
b11 8"
1#"
0A
0V
01
1W
0Y
1!"
1z
1j
1e
1b
0y
0q
0i
0d
1+"
b10 /
0)"
b11 $
b11 *
b11 ,
b11 7"
b10 +
1(
#40
0(
#45
1,"
1u
0*"
0("
b10 #
b10 )
b10 .
b10 8"
0~
0s
0>
b100 ^
0r
12
1O
1A
1V
0P
0W
1y
1q
1i
1d
b10 $
b10 *
b10 ,
b10 7"
b11 /
1)"
b11 +
1(
#50
0(
#55
1("
0*"
1r
b101 ^
0s
1?
b110 #
b110 )
b110 .
b110 8"
1&"
02
0A
0O
0@
0V
00
18
1P
1W
0X
1Y
1%"
1""
1t
1l
1f
1c
0!"
0z
0j
0e
0b
0y
0q
0i
0d
1-"
0+"
b100 /
0)"
b110 $
b110 *
b110 ,
b110 7"
b100 +
1(
#60
0(
#65
1*"
1s
0("
b110 ^
0r
0?
b111 #
b111 )
b111 .
b111 8"
1~
1A
1@
1V
08
0W
1y
1q
1i
1d
b111 $
b111 *
b111 ,
b111 7"
b101 /
1)"
b101 +
1(
#70
0(
#75
1("
b111 ^
1r
b101 #
b101 )
b101 .
b101 8"
0#"
0A
1U
0V
0T
1W
0Y
1!"
1z
1j
1e
1b
0y
0q
0i
0d
1+"
b110 /
0)"
b101 $
b101 *
b101 ,
b101 7"
b110 +
1(
#80
0(
#85
1."
1v
0,"
0u
0;
1=
1<
0*"
0("
b100 #
b100 )
b100 .
b100 8"
0~
0s
b1000 ^
0r
0S
12
1O
1A
1V
0P
0W
1y
1q
1i
1d
b100 $
b100 *
b100 ,
b100 7"
b111 /
1)"
b111 +
1(
#90
0(
#95
00"
0x
0=
1("
1."
0*"
1r
1v
1:
b1001 ^
0s
1>
1?
1S
b1100 #
b1100 )
b1100 .
b1100 8"
1'"
02
0A
0L
0U
0O
0@
0V
07
11
1T
18
1P
1W
0\
1X
1Y
1$"
1{
1k
1g
1_
0%"
0""
0t
0l
0f
0c
0!"
0z
0j
0e
0b
0y
0q
0i
0d
1/"
0-"
0+"
b1000 /
0)"
b1100 $
b1100 *
b1100 ,
b1100 7"
b1000 +
1(
#100
0(
#105
1*"
1s
0("
b1010 ^
0r
0?
b1101 #
b1101 )
b1101 .
b1101 8"
1~
1A
1@
1V
08
0W
1y
1q
1i
1d
b1101 $
b1101 *
b1101 ,
b1101 7"
b1001 /
1)"
b1001 +
1(
#110
0(
#115
1("
b1011 ^
1r
b1111 #
b1111 )
b1111 .
b1111 8"
1#"
0A
0V
01
1W
0Y
1!"
1z
1j
1e
1b
0y
0q
0i
0d
1+"
b1010 /
0)"
b1111 $
b1111 *
b1111 ,
b1111 7"
b1010 +
1(
#120
0(
#125
1,"
1u
0*"
0("
b1110 #
b1110 )
b1110 .
b1110 8"
0~
0s
0>
b1100 ^
0r
12
1O
1A
1V
0P
0W
1y
1q
1i
1d
b1110 $
b1110 *
b1110 ,
b1110 7"
b1011 /
1)"
b1011 +
1(
#130
0(
#135
1("
0*"
1r
b1010 #
b1010 )
b1010 .
b1010 8"
0&"
b1101 ^
0s
1?
02
0A
1M
0O
0@
0V
0N
18
1P
1W
0X
1Y
1%"
1""
1t
1l
1f
1c
0!"
0z
0j
0e
0b
0y
0q
0i
0d
1-"
0+"
b1100 /
0)"
b1010 $
b1010 *
b1010 ,
b1010 7"
b1100 +
1(
#140
0(
#145
1*"
1s
0("
b1110 ^
0r
0?
b1011 #
b1011 )
b1011 .
b1011 8"
1~
1A
1@
1V
08
0W
1y
1q
1i
1d
b1011 $
b1011 *
b1011 ,
b1011 7"
b1101 /
1)"
b1101 +
1(
#150
0(
#155
1("
b1111 ^
1r
b1001 #
b1001 )
b1001 .
b1001 8"
0#"
0A
1U
0V
0T
1W
0Y
1!"
1z
1j
1e
1b
0y
0q
0i
0d
1+"
b1110 /
0)"
b1001 $
b1001 *
b1001 ,
b1001 7"
b1110 +
1(
#160
0(
#165
10"
1x
0."
0,"
0v
0:
0u
1L
1=
0*"
0("
b1000 #
b1000 )
b1000 .
b1000 8"
0~
0s
b10000 ^
0r
0S
12
1O
1A
1V
0P
0W
1y
1q
1i
1d
b1000 $
b1000 *
b1000 ,
b1000 7"
b1111 /
1)"
b1111 +
1(
#170
0(
#175
02"
1;
b0 ]
0o
10"
0=
0<
1("
1F
1x
0."
0*"
1r
0v
b10001 ^
0s
1>
1?
1S
0G
09
02
0A
0L
0M
0U
0O
0@
0V
1J
10
1N
11
1T
18
1P
1W
1\
1X
1Y
b11000 #
b11000 )
b11000 .
b11000 8"
1|
1w
1m
1h
0$"
0{
0k
0g
0_
0%"
0""
0t
0l
0f
0c
0!"
0z
0j
0e
0b
0y
0q
0i
0d
11"
0/"
0-"
0+"
b10000 /
0)"
b11000 $
b11000 *
b11000 ,
b11000 7"
b10000 +
1(
#180
0(
#185
1*"
1s
0("
b10010 ^
0r
0?
b11001 #
b11001 )
b11001 .
b11001 8"
1~
1A
1@
1V
08
0W
1y
1q
1i
1d
b11001 $
b11001 *
b11001 ,
b11001 7"
b10001 /
1)"
b10001 +
1(
#190
0(
#195
1("
b10011 ^
1r
b11011 #
b11011 )
b11011 .
b11011 8"
1#"
0A
0V
01
1W
0Y
1!"
1z
1j
1e
1b
0y
0q
0i
0d
1+"
b10010 /
0)"
b11011 $
b11011 *
b11011 ,
b11011 7"
b10010 +
1(
#200
0(
#205
1,"
1u
0*"
0("
b11010 #
b11010 )
b11010 .
b11010 8"
0~
0s
0>
b10100 ^
0r
12
1O
1A
1V
0P
0W
1y
1q
1i
1d
b11010 $
b11010 *
b11010 ,
b11010 7"
b10011 /
1)"
b10011 +
1(
#210
0(
#215
1("
0*"
1r
b10101 ^
0s
1?
b11110 #
b11110 )
b11110 .
b11110 8"
1&"
02
0A
0O
0@
0V
00
18
1P
1W
0X
1Y
1%"
1""
1t
1l
1f
1c
0!"
0z
0j
0e
0b
0y
0q
0i
0d
1-"
0+"
b10100 /
0)"
b11110 $
b11110 *
b11110 ,
b11110 7"
b10100 +
1(
#220
0(
#225
1*"
1s
0("
b10110 ^
0r
0?
b11111 #
b11111 )
b11111 .
b11111 8"
1~
1A
1@
1V
08
0W
1y
1q
1i
1d
b11111 $
b11111 *
b11111 ,
b11111 7"
b10101 /
1)"
b10101 +
1(
#230
0(
#235
1("
b10111 ^
1r
b11101 #
b11101 )
b11101 .
b11101 8"
0#"
0A
1U
0V
0T
1W
0Y
1!"
1z
1j
1e
1b
0y
0q
0i
0d
1+"
b10110 /
0)"
b11101 $
b11101 *
b11101 ,
b11101 7"
b10110 +
1(
#240
0(
#245
1."
1v
0,"
0u
0;
1=
1<
0*"
0("
b11100 #
b11100 )
b11100 .
b11100 8"
0~
0s
b11000 ^
0r
0S
12
1O
1A
1V
0P
0W
1y
1q
1i
1d
b11100 $
b11100 *
b11100 ,
b11100 7"
b10111 /
1)"
b10111 +
1(
#250
0(
#255
02"
b0 ]
0o
10"
1F
1x
0G
09
0=
1("
1."
0*"
1r
b10100 #
b10100 )
b10100 .
b10100 8"
0'"
1J
1v
b11001 ^
0s
1>
1?
1S
0K
02
0A
1Q
0L
0U
0O
0@
0V
0R
11
1T
18
1P
1W
0\
1X
1Y
1$"
1{
1k
1g
1_
0%"
0""
0t
0l
0f
0c
0!"
0z
0j
0e
0b
0y
0q
0i
0d
1/"
0-"
0+"
b11000 /
0)"
b10100 $
b10100 *
b10100 ,
b10100 7"
b11000 +
1(
#260
0(
